{"showTimer":false,"isDarkMode":true,"disableAds":false,"questionsSolved":[{"id":6,"skipped":true,"userSolution":"select *\nfrom order_details as o\njoin products as p\non o.product_id = p.product_id\ngroup by product_id;\n\n\n\n"},{"id":32,"skipped":true,"userSolution":"SELECT * FROM products\n\n"},{"id":55,"skipped":true,"userSolution":"SELECT * FROM patients\n\n"},{"id":68,"skipped":true,"userSolution":"SELECT product_id,\nround( quantity + 5) as Total_quantity\nFROM order_details;\n\n\n select * from order_details\n"},{"id":16,"skipped":true,"userSolution":"SELECT * FROM products\n\n"},{"id":65,"skipped":true,"userSolution":"SELECT * FROM suppliers\n\nselect company_name, 'SU' as aria from suppliers\nunion all\nselect company_name, 'SH' from shippers;"}],"autoRun":false,"autocomplete":true,"editorFontSize":16,"persistEditorText":false,"editorText":"SELECT * FROM products\n\n/*\n  Start by selecting a question by pressing 'Start' or 'View All Questions'.\n  Use the resources and information about the database from the left panel to help.\n  Press the run button to execute the query.\n  Question is automatically validated every time you execute the query.\n  Make your output match the expected output.\n\n\n  Keybinds:\n    [ctrl + enter]: Execute the SQL\n    [ctrl + q]: Auto-format the SQL\n*/","queryTimes":[{"id":6,"time":7007},{"id":32,"time":16003},{"id":55,"time":4000},{"id":68,"time":5007},{"id":16,"time":1005},{"id":65,"time":12002}],"filterState":{"selectedKeywordFilter":"Case","selectedDifficultyFilter":"ALL","selectedCompletedFilter":"ALL","selectedDatabaseFilter":"Northwind"}}